jukeaudio/__init__.py
jukeaudio/exceptions.py
jukeaudio/jukeaudio.py
jukeaudio/jukeaudio_v3.py
jukeaudio-0.0.11.dist-info/licenses/LICENSE
jukeaudio-0.0.11.dist-info/METADATA
jukeaudio-0.0.11.dist-info/WHEEL
jukeaudio-0.0.11.dist-info/top_level.txt
jukeaudio-0.0.11.dist-info/RECORD
