Metadata-Version: 2.4
Name: JukeAudio
Version: 0.0.11
Summary: Python client for the JukeAudio API
Author-email: Paul Karimov <paul_karimov@outlook.com>
Project-URL: Homepage, https://github.com/pkarimov/jukeaudio
Project-URL: Bug Tracker, https://github.com/pkarimov/jukeaudio/issues
Classifier: Programming Language :: Python :: 3
Classifier: License :: OSI Approved :: MIT License
Classifier: Operating System :: OS Independent
Requires-Python: >=3.7
License-File: LICENSE
Dynamic: license-file
